autoboot_web/__init__.py
autoboot_web/autoboot-web.schema.json
autoboot_web/http_properties.py
autoboot_web/runner.py
autoboot_web/web_properties.py
autoboot_web/discovery/__init__.py
autoboot_web/discovery/nacos/__init__.py
autoboot_web/discovery/nacos/nacos_factory.py
autoboot_web/discovery/nacos/nacos_properties.py
autoboot_web/middleware/__init__.py
autoboot_web/middleware/uniform.py
autoboot_web/mvc/__init__.py
autoboot_web/mvc/apply_router.py
autoboot_web/mvc/annotation/__init__.py
autoboot_web/mvc/annotation/controller.py
autoboot_web-0.9.2.dist-info/LICENSE.txt
autoboot_web-0.9.2.dist-info/METADATA
autoboot_web-0.9.2.dist-info/WHEEL
autoboot_web-0.9.2.dist-info/top_level.txt
autoboot_web-0.9.2.dist-info/RECORD
