Metadata-Version: 2.1
Name: autoboot-web
Version: 0.9.2
Summary: Web starter build with autoboot and FastAPI
Home-page: https://github.com/yizzuide/autoboot_web
Author: yizzuide
Author-email: fu837014586@163.com
License: MIT
Keywords: autoboot,web,FastAPI
Classifier: Development Status :: 5 - Production/Stable
Classifier: Operating System :: OS Independent
Classifier: Intended Audience :: Developers
Classifier: Programming Language :: Python :: 3.8
Classifier: License :: OSI Approved :: MIT License
Requires-Python: >=3.8
License-File: LICENSE.txt
Requires-Dist: autoboot <1.0,>=0.12.2
Requires-Dist: fastapi <1.0,>=0.110.0
Requires-Dist: uvicorn <1.0,>=0.27.0
Requires-Dist: aiohttp <4.0,>=3.8.1
Requires-Dist: aiofiles <24.0,>=23.1.0
Provides-Extra: extra
Requires-Dist: Jinja2 >=3.1.2 ; extra == 'extra'
Requires-Dist: starlette-csrf >=1.4.0 ; extra == 'extra'
Provides-Extra: nacos
Requires-Dist: nacos-sdk-python ==0.1.16 ; extra == 'nacos'
